clifs/__init__.py
clifs/__main__.py
clifs/clifs_plugin.py
clifs/plugins/__init__.py
clifs/plugins/backup.py
clifs/plugins/como.py
clifs/plugins/delete.py
clifs/plugins/disc_usage.py
clifs/plugins/edit.py
clifs/plugins/rename.py
clifs/plugins/tree.py
clifs/utils_cli.py
clifs/utils_fs.py
clifs-2.0.0.dist-info/licenses/LICENSE
clifs-2.0.0.dist-info/WHEEL
clifs-2.0.0.dist-info/entry_points.txt
clifs-2.0.0.dist-info/METADATA
clifs-2.0.0.dist-info/RECORD
