Metadata-Version: 2.4
Name: clifs
Version: 2.0.0
Summary: Command line interface for basic file system operations.
Keywords: file system,command line
Author: Felix Segerer
Author-email: Felix Segerer <don.felice@gmx.net>
License-File: LICENSE
Classifier: Programming Language :: Python :: 3
Requires-Dist: rich>=13.7.0
Requires-Dist: python-dateutil
Requires-Dist: tomli>=2.3.0 ; python_full_version < '3.11'
Requires-Python: >=3.10
Project-URL: Source code, https://github.com/Don-Felice/clifs
